{"basic":["刀","Sword","87"],"extended":[{"jlpt":["jlpt-n3"],"tags":["wanikani2"],"japanese":[{"word":"刀","reading":"かたな"},{"word":"刀","reading":"とう"}],"senses":[["sword (esp. Japanese single-edged)","katana"],["scalpel"],["chisel","burin","graver"],["knife money (knife-shaped commodity money used in ancient China)"],["Backsword"]]},{"jlpt":["jlpt-n3","jlpt-n1"],"tags":[],"japanese":[{"word":"鋏","reading":"はさみ"},{"word":"剪刀","reading":"はさみ"},{"reading":"ハサミ"}],"senses":[["scissors","shears","clippers"],["hole punch"]]},{"jlpt":["jlpt-n2"],"tags":[],"japanese":[{"word":"剃刀","reading":"かみそり"},{"word":"剃刀","reading":"かみすり"},{"word":"剃刀","reading":"そり"},{"reading":"カミソリ"}],"senses":[["razor"],["Razor"]]}]}