{"basic":["刺","Thorn","446"],"extended":[{"jlpt":["jlpt-n2"],"tags":["wanikani28"],"japanese":[{"word":"刺身","reading":"さしみ"},{"word":"刺し身","reading":"さしみ"}],"senses":[["sashimi (raw sliced fish, shellfish or crustaceans)"],["Sashimi"]]},{"jlpt":["jlpt-n2"],"tags":["wanikani26"],"japanese":[{"word":"名刺","reading":"めいし"}],"senses":[["business card"],["Business card"]]},{"jlpt":["jlpt-n1"],"tags":[],"japanese":[{"word":"刺繍","reading":"ししゅう"},{"word":"刺しゅう","reading":"ししゅう"},{"word":"刺繡","reading":"ししゅう"}],"senses":[["embroidery"],["Embroidery"]]},{"jlpt":["jlpt-n3"],"tags":["wanikani26"],"japanese":[{"word":"刺激","reading":"しげき"},{"word":"刺戟","reading":"しげき"},{"word":"剌激","reading":"しげき"}],"senses":[["stimulus","impetus","incentive","encouragement","motivation","provocation","excitement","thrill"]]},{"jlpt":["jlpt-n3","jlpt-n1"],"tags":[],"japanese":[{"word":"苛々","reading":"いらいら"},{"word":"苛苛","reading":"いらいら"},{"word":"刺々","reading":"いらいら"},{"word":"刺刺","reading":"いらいら"},{"reading":"イライラ"}],"senses":[["to get irritated","to get annoyed","to be on the edge","to fret","to lose patience"]]},{"jlpt":["jlpt-n2"],"tags":["wanikani26"],"japanese":[{"word":"刺す","reading":"さす"}],"senses":[["to pierce","to stab","to prick","to stick","to thrust"],["to sting","to bite"],["to sew","to stitch","to embroider"],["to pole (a boat)"],["to catch (with a limed pole)"],["to put (a runner) out","to pick off"]]},{"jlpt":["jlpt-n2"],"tags":[],"japanese":[{"word":"刺さる","reading":"ささる"}],"senses":[["to stick into (of something with a sharp point)","to prick","to pierce","to get stuck (in)","to lodge (in)"],["to resonate emotionally","to move"]]},{"jlpt":["jlpt-n1"],"tags":[],"japanese":[{"word":"刺","reading":"とげ"},{"word":"棘","reading":"とげ"},{"reading":"トゲ"}],"senses":[["thorn","spine","prickle"],["splinter (esp. lodged in one's flesh)","hard sharp item (esp. lodged in one's throat, e.g. fish bone)"],["biting words"]]},{"jlpt":[],"tags":[],"japanese":[{"word":"風刺","reading":"ふうし"},{"word":"諷刺","reading":"ふうし"}],"senses":[["satire","irony","sarcasm"],["Satire"]]},{"jlpt":[],"tags":[],"japanese":[{"word":"突き刺す","reading":"つきさす"},{"word":"突きさす","reading":"つきさす"},{"word":"突刺す","reading":"つきさす"},{"word":"つき刺す","reading":"つきさす"}],"senses":[["to stab","to pierce","to thrust"]]},{"jlpt":[],"tags":["wanikani46"],"japanese":[{"word":"入れ墨","reading":"いれずみ"}],"senses":[["tattoo (esp. a traditional Japanese one)","tattooing"],["Tattoo"]]},{"jlpt":[],"tags":[],"japanese":[{"word":"刺し","reading":"さし"}],"senses":[["grain thief","sharpened tube for testing rice in bags"],["sashimi (sliced raw fish)"],["stabbing","piercing","pricking"]]},{"jlpt":["jlpt-n2"],"tags":["wanikani28"],"japanese":[{"word":"刺身","reading":"さしみ"},{"word":"刺し身","reading":"さしみ"}],"senses":[["sashimi (raw sliced fish, shellfish or crustaceans)"],["Sashimi"]]},{"jlpt":["jlpt-n2"],"tags":["wanikani26"],"japanese":[{"word":"名刺","reading":"めいし"}],"senses":[["business card"],["Business card"]]},{"jlpt":["jlpt-n1"],"tags":[],"japanese":[{"word":"刺繍","reading":"ししゅう"},{"word":"刺しゅう","reading":"ししゅう"},{"word":"刺繡","reading":"ししゅう"}],"senses":[["embroidery"],["Embroidery"]]},{"jlpt":["jlpt-n3"],"tags":["wanikani26"],"japanese":[{"word":"刺激","reading":"しげき"},{"word":"刺戟","reading":"しげき"},{"word":"剌激","reading":"しげき"}],"senses":[["stimulus","impetus","incentive","encouragement","motivation","provocation","excitement","thrill"]]},{"jlpt":["jlpt-n3","jlpt-n1"],"tags":[],"japanese":[{"word":"苛々","reading":"いらいら"},{"word":"苛苛","reading":"いらいら"},{"word":"刺々","reading":"いらいら"},{"word":"刺刺","reading":"いらいら"},{"reading":"イライラ"}],"senses":[["to get irritated","to get annoyed","to be on the edge","to fret","to lose patience"]]},{"jlpt":["jlpt-n2"],"tags":["wanikani26"],"japanese":[{"word":"刺す","reading":"さす"}],"senses":[["to pierce","to stab","to prick","to stick","to thrust"],["to sting","to bite"],["to sew","to stitch","to embroider"],["to pole (a boat)"],["to catch (with a limed pole)"],["to put (a runner) out","to pick off"]]},{"jlpt":["jlpt-n2"],"tags":[],"japanese":[{"word":"刺さる","reading":"ささる"}],"senses":[["to stick into (of something with a sharp point)","to prick","to pierce","to get stuck (in)","to lodge (in)"],["to resonate emotionally","to move"]]},{"jlpt":["jlpt-n1"],"tags":[],"japanese":[{"word":"刺","reading":"とげ"},{"word":"棘","reading":"とげ"},{"reading":"トゲ"}],"senses":[["thorn","spine","prickle"],["splinter (esp. lodged in one's flesh)","hard sharp item (esp. lodged in one's throat, e.g. fish bone)"],["biting words"]]},{"jlpt":[],"tags":[],"japanese":[{"word":"風刺","reading":"ふうし"},{"word":"諷刺","reading":"ふうし"}],"senses":[["satire","irony","sarcasm"],["Satire"]]},{"jlpt":[],"tags":[],"japanese":[{"word":"突き刺す","reading":"つきさす"},{"word":"突きさす","reading":"つきさす"},{"word":"突刺す","reading":"つきさす"},{"word":"つき刺す","reading":"つきさす"}],"senses":[["to stab","to pierce","to thrust"]]},{"jlpt":[],"tags":["wanikani46"],"japanese":[{"word":"入れ墨","reading":"いれずみ"}],"senses":[["tattoo (esp. a traditional Japanese one)","tattooing"],["Tattoo"]]},{"jlpt":[],"tags":[],"japanese":[{"word":"刺し","reading":"さし"}],"senses":[["grain thief","sharpened tube for testing rice in bags"],["sashimi (sliced raw fish)"],["stabbing","piercing","pricking"]]}]}