{"basic":["厘","Rin","190"],"extended":[{"jlpt":[],"tags":[],"japanese":[{"word":"厘","reading":"りん"},{"word":"厘","reading":"り"},{"word":"釐","reading":"り"}],"senses":[["one-hundredth","0.3 mm (one-hundredth of a sun)","0.1 percent (one-hundredth of a wari)","0.0375 grams (one-hundredth of a monme)"],["rin (monetary unit; 0.001 yen)"]]},{"jlpt":[],"tags":[],"japanese":[{"word":"厘","reading":"りん"},{"word":"厘","reading":"り"},{"word":"釐","reading":"り"}],"senses":[["one-hundredth","0.3 mm (one-hundredth of a sun)","0.1 percent (one-hundredth of a wari)","0.0375 grams (one-hundredth of a monme)"],["rin (monetary unit; 0.001 yen)"]]}]}