{"basic":["口","Mouth","11"],"extended":[{"jlpt":["jlpt-n4"],"tags":["wanikani1"],"japanese":[{"word":"人口","reading":"じんこう"}],"senses":[["population"],["common talk"],["Population"]]},{"jlpt":["jlpt-n2"],"tags":[],"japanese":[{"word":"蛇口","reading":"じゃぐち"},{"word":"じゃ口","reading":"じゃぐち"}],"senses":[["faucet","tap"],["Jaguchi"],["Tap (valve)"]]},{"jlpt":["jlpt-n1"],"tags":[],"japanese":[{"word":"無口","reading":"むくち"}],"senses":[["taciturn","reticent","quiet","silent","untalkative"],["Halter"]]},{"jlpt":["jlpt-n3"],"tags":[],"japanese":[{"word":"利口","reading":"りこう"},{"word":"俐巧","reading":"りこう"},{"word":"悧巧","reading":"りこう"},{"word":"利巧","reading":"りこう"}],"senses":[["clever","intelligent","wise","bright","sharp","sensible","smart","shrewd"],["well-behaved (esp. children and pets)","obedient","good"],["good (with words)"]]},{"jlpt":["jlpt-n2"],"tags":["wanikani6"],"japanese":[{"word":"早口","reading":"はやくち"},{"word":"早口","reading":"はやぐち"},{"word":"速口","reading":"はやくち"},{"word":"速口","reading":"はやぐち"}],"senses":[["fast-talking","rapid talking"]]},{"jlpt":["jlpt-n2"],"tags":["wanikani33"],"japanese":[{"word":"窓口","reading":"まどぐち"}],"senses":[["counter","window","teller window","ticket window"],["contact person","point of contact"]]},{"jlpt":["jlpt-n2"],"tags":["wanikani33"],"japanese":[{"word":"裏口","reading":"うらぐち"}],"senses":[["backdoor","rear entrance"],["unauthorized","illicit","illegal"]]},{"jlpt":["jlpt-n2","jlpt-n1"],"tags":[],"japanese":[{"word":"出入り口","reading":"でいりぐち"},{"word":"出入口","reading":"でいりぐち"}],"senses":[["exit and entrance"]]},{"jlpt":["jlpt-n1"],"tags":[],"japanese":[{"word":"閉口","reading":"へいこう"}],"senses":[["to be stumped","to be at a loss","to be at one's wits' end","to be nonplussed"],["to be fed up","to be tired (of)","to be unable to bear","to be annoyed"]]},{"jlpt":["jlpt-n1","jlpt-n5"],"tags":["wanikani1"],"japanese":[{"word":"入口","reading":"いりぐち"},{"word":"入口","reading":"いりくち"},{"word":"入口","reading":"はいりぐち"},{"word":"入口","reading":"はいりくち"},{"word":"入り口","reading":"いりぐち"},{"word":"入り口","reading":"いりくち"},{"word":"入り口","reading":"はいりぐち"},{"word":"入り口","reading":"はいりくち"}],"senses":[["entrance","entry","gate","approach","mouth"]]},{"jlpt":["jlpt-n5"],"tags":["wanikani2"],"japanese":[{"word":"出口","reading":"でぐち"}],"senses":[["exit","gateway","way out"],["outlet","vent","leak"]]},{"jlpt":[],"tags":["wanikani19"],"japanese":[{"word":"非常口","reading":"ひじょうぐち"}],"senses":[["emergency exit"],["Emergency exit"]]},{"jlpt":["jlpt-n3","jlpt-n1"],"tags":["wanikani14"],"japanese":[{"word":"悪口","reading":"わるぐち"},{"word":"悪口","reading":"わるくち"},{"word":"悪口","reading":"あっこう"},{"word":"惡口","reading":"わるぐち"},{"word":"惡口","reading":"わるくち"},{"word":"惡口","reading":"あっこう"}],"senses":[["slander","bad-mouthing","abuse","insult","speaking ill (of)"]]},{"jlpt":[],"tags":[],"japanese":[{"word":"傷口","reading":"きずぐち"},{"word":"疵口","reading":"きずぐち"}],"senses":[["(opening of) a wound","(mouth of a) wound","cut"]]},{"jlpt":[],"tags":[],"japanese":[{"word":"陰口","reading":"かげぐち"},{"word":"蔭口","reading":"かげぐち"},{"word":"影口","reading":"かげぐち"}],"senses":[["malicious gossip","backbiting","speaking ill behind someone's back"]]},{"jlpt":[],"tags":[],"japanese":[{"word":"糸口","reading":"いとぐち"},{"word":"緒","reading":"いとぐち"},{"word":"絲口","reading":"いとぐち"}],"senses":[["beginning","start","first step"],["clue","lead","hint"],["thread end"]]},{"jlpt":[],"tags":[],"japanese":[{"word":"口々","reading":"くちぐち"},{"word":"口口","reading":"くちぐち"}],"senses":[["every person","every mouth"],["every entrance"]]},{"jlpt":[],"tags":[],"japanese":[{"word":"間口","reading":"まぐち"}],"senses":[["frontage","width (of a building, plot of land, etc.)"],["breadth (e.g. of one's knowledge)","scope (e.g. of one's work)","range"]]},{"jlpt":[],"tags":["wanikani46"],"japanese":[{"word":"辛口","reading":"からくち"}],"senses":[["dry taste (e.g. sake, wine)"],["a liking for sake","one who likes sake"],["salty (taste)"],["harsh","scathing"]]},{"jlpt":[],"tags":[],"japanese":[{"word":"語り口","reading":"かたりくち"}],"senses":[["way of reciting","way of telling a story"]]},{"jlpt":["jlpt-n4"],"tags":["wanikani1"],"japanese":[{"word":"人口","reading":"じんこう"}],"senses":[["population"],["common talk"],["Population"]]},{"jlpt":["jlpt-n2"],"tags":[],"japanese":[{"word":"蛇口","reading":"じゃぐち"},{"word":"じゃ口","reading":"じゃぐち"}],"senses":[["faucet","tap"],["Jaguchi"],["Tap (valve)"]]},{"jlpt":["jlpt-n1"],"tags":[],"japanese":[{"word":"無口","reading":"むくち"}],"senses":[["taciturn","reticent","quiet","silent","untalkative"],["Halter"]]},{"jlpt":["jlpt-n3"],"tags":[],"japanese":[{"word":"利口","reading":"りこう"},{"word":"俐巧","reading":"りこう"},{"word":"悧巧","reading":"りこう"},{"word":"利巧","reading":"りこう"}],"senses":[["clever","intelligent","wise","bright","sharp","sensible","smart","shrewd"],["well-behaved (esp. children and pets)","obedient","good"],["good (with words)"]]},{"jlpt":["jlpt-n2"],"tags":["wanikani6"],"japanese":[{"word":"早口","reading":"はやくち"},{"word":"早口","reading":"はやぐち"},{"word":"速口","reading":"はやくち"},{"word":"速口","reading":"はやぐち"}],"senses":[["fast-talking","rapid talking"]]},{"jlpt":["jlpt-n2"],"tags":["wanikani33"],"japanese":[{"word":"窓口","reading":"まどぐち"}],"senses":[["counter","window","teller window","ticket window"],["contact person","point of contact"]]},{"jlpt":["jlpt-n2"],"tags":["wanikani33"],"japanese":[{"word":"裏口","reading":"うらぐち"}],"senses":[["backdoor","rear entrance"],["unauthorized","illicit","illegal"]]},{"jlpt":["jlpt-n2","jlpt-n1"],"tags":[],"japanese":[{"word":"出入り口","reading":"でいりぐち"},{"word":"出入口","reading":"でいりぐち"}],"senses":[["exit and entrance"]]},{"jlpt":["jlpt-n1"],"tags":[],"japanese":[{"word":"閉口","reading":"へいこう"}],"senses":[["to be stumped","to be at a loss","to be at one's wits' end","to be nonplussed"],["to be fed up","to be tired (of)","to be unable to bear","to be annoyed"]]},{"jlpt":["jlpt-n1","jlpt-n5"],"tags":["wanikani1"],"japanese":[{"word":"入口","reading":"いりぐち"},{"word":"入口","reading":"いりくち"},{"word":"入口","reading":"はいりぐち"},{"word":"入口","reading":"はいりくち"},{"word":"入り口","reading":"いりぐち"},{"word":"入り口","reading":"いりくち"},{"word":"入り口","reading":"はいりぐち"},{"word":"入り口","reading":"はいりくち"}],"senses":[["entrance","entry","gate","approach","mouth"]]},{"jlpt":["jlpt-n5"],"tags":["wanikani2"],"japanese":[{"word":"出口","reading":"でぐち"}],"senses":[["exit","gateway","way out"],["outlet","vent","leak"]]},{"jlpt":[],"tags":["wanikani19"],"japanese":[{"word":"非常口","reading":"ひじょうぐち"}],"senses":[["emergency exit"],["Emergency exit"]]},{"jlpt":["jlpt-n3","jlpt-n1"],"tags":["wanikani14"],"japanese":[{"word":"悪口","reading":"わるぐち"},{"word":"悪口","reading":"わるくち"},{"word":"悪口","reading":"あっこう"},{"word":"惡口","reading":"わるぐち"},{"word":"惡口","reading":"わるくち"},{"word":"惡口","reading":"あっこう"}],"senses":[["slander","bad-mouthing","abuse","insult","speaking ill (of)"]]},{"jlpt":[],"tags":[],"japanese":[{"word":"傷口","reading":"きずぐち"},{"word":"疵口","reading":"きずぐち"}],"senses":[["(opening of) a wound","(mouth of a) wound","cut"]]},{"jlpt":[],"tags":[],"japanese":[{"word":"陰口","reading":"かげぐち"},{"word":"蔭口","reading":"かげぐち"},{"word":"影口","reading":"かげぐち"}],"senses":[["malicious gossip","backbiting","speaking ill behind someone's back"]]},{"jlpt":[],"tags":[],"japanese":[{"word":"糸口","reading":"いとぐち"},{"word":"緒","reading":"いとぐち"},{"word":"絲口","reading":"いとぐち"}],"senses":[["beginning","start","first step"],["clue","lead","hint"],["thread end"]]},{"jlpt":[],"tags":[],"japanese":[{"word":"間口","reading":"まぐち"}],"senses":[["frontage","width (of a building, plot of land, etc.)"],["breadth (e.g. of one's knowledge)","scope (e.g. of one's work)","range"]]},{"jlpt":[],"tags":["wanikani46"],"japanese":[{"word":"辛口","reading":"からくち"}],"senses":[["dry taste (e.g. sake, wine)"],["a liking for sake","one who likes sake"],["salty (taste)"],["harsh","scathing"]]},{"jlpt":[],"tags":[],"japanese":[{"word":"口々","reading":"くちぐち"},{"word":"口口","reading":"くちぐち"}],"senses":[["every person","every mouth"],["every entrance"]]},{"jlpt":[],"tags":[],"japanese":[{"word":"語り口","reading":"かたりくち"}],"senses":[["way of reciting","way of telling a story"]]},{"jlpt":[],"tags":[],"japanese":[{"word":"改札口","reading":"かいさつぐち"}],"senses":[["ticket barrier","ticket gate","wicket"]]},{"jlpt":[],"tags":[],"japanese":[{"word":"河口","reading":"かこう"},{"word":"河口","reading":"かわぐち"},{"word":"川口","reading":"かわぐち"}],"senses":[["mouth of river","estuary"],["Kawaguchi"]]},{"jlpt":[],"tags":[],"japanese":[{"word":"一口","reading":"ひとくち"},{"word":"ひと口","reading":"ひとくち"}],"senses":[["mouthful","morsel","bite"],["gulp","sip","draft","draught"],["one word","in short"],["one share","one contribution"]]},{"jlpt":[],"tags":[],"japanese":[{"word":"大口","reading":"おおぐち"},{"word":"大口","reading":"おおくち"}],"senses":[["big mouth","mouth opened wide"],["boastful speech","tall talk","bragging","boasting"],["large amount","large quantity"]]},{"jlpt":[],"tags":[],"japanese":[{"word":"手口","reading":"てぐち"}],"senses":[["modus operandi","criminal technique","trick"]]},{"jlpt":[],"tags":[],"japanese":[{"word":"小口","reading":"こぐち"}],"senses":[["cut end","edge (of a page, etc.)"],["small amount","small quantity","small sum"],["beginning","clue"],["tiger's den","jaws of death","dangerous place"]]},{"jlpt":[],"tags":[],"japanese":[{"word":"秋口","reading":"あきぐち"}],"senses":[["beginning of autumn","beginning of fall"]]},{"jlpt":[],"tags":[],"japanese":[{"word":"北口","reading":"きたぐち"}],"senses":[["north entrance"]]},{"jlpt":[],"tags":[],"japanese":[{"word":"異口同音","reading":"いくどうおん"},{"word":"異句同音","reading":"いくどうおん"},{"word":"異口同音","reading":"いこうどうおん"}],"senses":[["(saying) with one voice","unanimously","in chorus","in unison","as one"]]},{"jlpt":[],"tags":[],"japanese":[{"word":"開口","reading":"かいこう"}],"senses":[["opening","aperture (e.g. camera)"],["opening one's mouth","beginning to speak"],["open","broad"]]},{"jlpt":[],"tags":["wanikani8"],"japanese":[{"word":"東口","reading":"ひがしぐち"}],"senses":[["east entrance"]]},{"jlpt":[],"tags":[],"japanese":[{"word":"取り口","reading":"とりくち"},{"word":"取口","reading":"とりくち"}],"senses":[["technique","techniques"]]},{"jlpt":[],"tags":["wanikani8"],"japanese":[{"word":"南口","reading":"みなみぐち"}],"senses":[["south entrance"]]},{"jlpt":[],"tags":[],"japanese":[{"word":"西口","reading":"にしぐち"}],"senses":[["west entrance"]]},{"jlpt":[],"tags":[],"japanese":[{"word":"水口","reading":"みずぐち"}],"senses":[["spout"]]},{"jlpt":[],"tags":[],"japanese":[{"word":"切り口","reading":"きりくち"},{"word":"切口","reading":"きりくち"},{"word":"截り口","reading":"きりくち"}],"senses":[["cut end","section","opening","slit"],["point of view","(different) perspective","new approach"]]},{"jlpt":[],"tags":[],"japanese":[{"word":"口々に","reading":"くちぐちに"},{"word":"口口に","reading":"くちぐちに"}],"senses":[["each and every person (saying)","one and all","unanimously","in unison","separately","individually"]]},{"jlpt":[],"tags":[],"japanese":[{"word":"火口","reading":"ひぐち"}],"senses":[["burner","nozzle","origin of a fire"]]}]}