{"basic":["夜","Night","1115"],"extended":[{"jlpt":["jlpt-n3","jlpt-n5"],"tags":["wanikani2"],"japanese":[{"word":"夕べ","reading":"ゆうべ"},{"word":"昨夜","reading":"ゆうべ"},{"word":"昨夜","reading":"さくや"},{"word":"昨夜","reading":"ゆんべ"}],"senses":[["evening"],["last night","yesterday evening"]]},{"jlpt":["jlpt-n2"],"tags":["wanikani12"],"japanese":[{"word":"深夜","reading":"しんや"}],"senses":[["late at night"],["Midnight"]]},{"jlpt":["jlpt-n4"],"tags":["wanikani6"],"japanese":[{"word":"今夜","reading":"こんや"}],"senses":[["this evening","tonight"]]},{"jlpt":["jlpt-n3"],"tags":["wanikani41"],"japanese":[{"word":"徹夜","reading":"てつや"}],"senses":[["staying up all night"]]},{"jlpt":["jlpt-n1"],"tags":[],"japanese":[{"word":"日夜","reading":"にちや"}],"senses":[["day and night","around the clock","always","constantly"]]},{"jlpt":[],"tags":[],"japanese":[{"word":"真夜中","reading":"まよなか"}],"senses":[["dead of night","midnight"]]},{"jlpt":[],"tags":[],"japanese":[{"word":"一夜","reading":"いちや"},{"word":"一夜","reading":"ひとや"},{"word":"一夜","reading":"ひとよ"}],"senses":[["one night","all night","overnight","one evening"]]},{"jlpt":[],"tags":[],"japanese":[{"word":"昼夜","reading":"ちゅうや"}],"senses":[["day and night"]]},{"jlpt":[],"tags":[],"japanese":[{"word":"前夜","reading":"ぜんや"}],"senses":[["last night","the previous night"],["night before (Christmas, etc.)","eve (of festival, major event, etc.)"]]},{"jlpt":[],"tags":[],"japanese":[{"word":"月夜","reading":"つきよ"}],"senses":[["moonlit night"]]},{"jlpt":[],"tags":[],"japanese":[{"word":"通夜","reading":"つや"},{"word":"通夜","reading":"つうや"}],"senses":[["all-night vigil over a body","wake"],["Wake (ceremony)"]]},{"jlpt":[],"tags":[],"japanese":[{"word":"同夜","reading":"どうや"}],"senses":[["the same night","that night"]]},{"jlpt":[],"tags":[],"japanese":[{"word":"前夜祭","reading":"ぜんやさい"}],"senses":[["the eve (of a festival) (e.g. Christmas Eve)"]]},{"jlpt":["jlpt-n3","jlpt-n5"],"tags":["wanikani2"],"japanese":[{"word":"夕べ","reading":"ゆうべ"},{"word":"昨夜","reading":"ゆうべ"},{"word":"昨夜","reading":"さくや"},{"word":"昨夜","reading":"ゆんべ"}],"senses":[["evening"],["last night","yesterday evening"]]},{"jlpt":["jlpt-n2"],"tags":["wanikani12"],"japanese":[{"word":"深夜","reading":"しんや"}],"senses":[["late at night"],["Midnight"]]},{"jlpt":["jlpt-n4"],"tags":["wanikani6"],"japanese":[{"word":"今夜","reading":"こんや"}],"senses":[["this evening","tonight"]]},{"jlpt":["jlpt-n3"],"tags":["wanikani41"],"japanese":[{"word":"徹夜","reading":"てつや"}],"senses":[["staying up all night"]]},{"jlpt":["jlpt-n1"],"tags":[],"japanese":[{"word":"日夜","reading":"にちや"}],"senses":[["day and night","around the clock","always","constantly"]]},{"jlpt":[],"tags":[],"japanese":[{"word":"真夜中","reading":"まよなか"}],"senses":[["dead of night","midnight"]]},{"jlpt":[],"tags":[],"japanese":[{"word":"一夜","reading":"いちや"},{"word":"一夜","reading":"ひとや"},{"word":"一夜","reading":"ひとよ"}],"senses":[["one night","all night","overnight","one evening"]]},{"jlpt":[],"tags":[],"japanese":[{"word":"昼夜","reading":"ちゅうや"}],"senses":[["day and night"]]},{"jlpt":[],"tags":[],"japanese":[{"word":"前夜","reading":"ぜんや"}],"senses":[["last night","the previous night"],["night before (Christmas, etc.)","eve (of festival, major event, etc.)"]]},{"jlpt":[],"tags":[],"japanese":[{"word":"月夜","reading":"つきよ"}],"senses":[["moonlit night"]]},{"jlpt":[],"tags":[],"japanese":[{"word":"通夜","reading":"つや"},{"word":"通夜","reading":"つうや"}],"senses":[["all-night vigil over a body","wake"],["Wake (ceremony)"]]},{"jlpt":[],"tags":[],"japanese":[{"word":"同夜","reading":"どうや"}],"senses":[["the same night","that night"]]},{"jlpt":[],"tags":[],"japanese":[{"word":"前夜祭","reading":"ぜんやさい"}],"senses":[["the eve (of a festival) (e.g. Christmas Eve)"]]}]}