{
  "basic": ["提", "Propose", "718"],
  "extended": [
    {
      "jlpt": ["jlpt-n1"],
      "tags": [],
      "japanese": [{ "word": "前提", "reading": "ぜんてい" }],
      "senses": [
        ["condition", "assumption", "prerequisite", "hypothesis"],
        ["intention", "intent", "aim", "goal"],
        ["premise (in logic)"],
        ["Presupposition"]
      ]
    },
    {
      "jlpt": [],
      "tags": [],
      "japanese": [
        { "word": "手提げ", "reading": "てさげ" },
        { "word": "手提", "reading": "てさげ" },
        { "word": "手堤げ", "reading": "てさげ" },
        { "word": "手堤", "reading": "てさげ" }
      ],
      "senses": [["handbag", "purse"]]
    },
    {
      "jlpt": [],
      "tags": [],
      "japanese": [{ "word": "大前提", "reading": "だいぜんてい" }],
      "senses": [
        ["major premise (in a syllogism)"],
        ["important condition", "basic premise", "basic assumption"],
        [
          "something that should be obvious to all",
          "something that should not have to be argued",
          "something that goes without mentioning"
        ]
      ]
    },
    {
      "jlpt": ["jlpt-n1"],
      "tags": [],
      "japanese": [{ "word": "前提", "reading": "ぜんてい" }],
      "senses": [
        ["condition", "assumption", "prerequisite", "hypothesis"],
        ["intention", "intent", "aim", "goal"],
        ["premise (in logic)"],
        ["Presupposition"]
      ]
    },
    {
      "jlpt": [],
      "tags": [],
      "japanese": [
        { "word": "手提げ", "reading": "てさげ" },
        { "word": "手提", "reading": "てさげ" },
        { "word": "手堤げ", "reading": "てさげ" },
        { "word": "手堤", "reading": "てさげ" }
      ],
      "senses": [["handbag", "purse"]]
    },
    {
      "jlpt": [],
      "tags": [],
      "japanese": [{ "word": "大前提", "reading": "だいぜんてい" }],
      "senses": [
        ["major premise (in a syllogism)"],
        ["important condition", "basic premise", "basic assumption"],
        [
          "something that should be obvious to all",
          "something that should not have to be argued",
          "something that goes without mentioning"
        ]
      ]
    }
  ]
}
