{"basic":["栗","Chestnut","1735"],"extended":[{"jlpt":[],"tags":[],"japanese":[{"word":"団栗","reading":"どんぐり"},{"word":"橡","reading":"どんぐり"},{"reading":"ドングリ"}],"senses":[["acorn"]]},{"jlpt":[],"tags":[],"japanese":[{"word":"栗","reading":"くり"},{"reading":"クリ"}],"senses":[["Japanese chestnut (Castanea crenata)"],["Japanese Chestnut"]]},{"jlpt":[],"tags":[],"japanese":[{"word":"団栗","reading":"どんぐり"},{"word":"橡","reading":"どんぐり"},{"reading":"ドングリ"}],"senses":[["acorn"]]},{"jlpt":[],"tags":[],"japanese":[{"word":"栗","reading":"くり"},{"reading":"クリ"}],"senses":[["Japanese chestnut (Castanea crenata)"],["Japanese Chestnut"]]}]}