{"basic":["武","Warrior","403"],"extended":[{"jlpt":["jlpt-n3"],"tags":["wanikani24"],"japanese":[{"word":"武器","reading":"ぶき"}],"senses":[["weapon","arms","ordnance"],["weapon (something used to gain an advantage)","asset"],["Weapon"]]},{"jlpt":["jlpt-n2"],"tags":["wanikani24"],"japanese":[{"word":"武士","reading":"ぶし"},{"word":"武士","reading":"もののふ"},{"word":"武夫","reading":"ぶふ"}],"senses":[["warrior","samurai"],["Mononofu"],["Samurai"]]},{"jlpt":["jlpt-n1"],"tags":["wanikani33"],"japanese":[{"word":"武装","reading":"ぶそう"}],"senses":[["arms","armament"]]},{"jlpt":["jlpt-n1"],"tags":[],"japanese":[{"word":"武力","reading":"ぶりょく"}],"senses":[["armed might","military power","the sword","force"]]},{"jlpt":[],"tags":[],"japanese":[{"word":"核武装","reading":"かくぶそう"}],"senses":[["nuclear arms"]]},{"jlpt":[],"tags":["wanikani24"],"japanese":[{"word":"武道","reading":"ぶどう"}],"senses":[["martial arts","military arts","Bushido"],["Budō"]]},{"jlpt":[],"tags":[],"japanese":[{"word":"武将","reading":"ぶしょう"}],"senses":[["military commander"]]},{"jlpt":[],"tags":[],"japanese":[{"word":"武者","reading":"むしゃ"}],"senses":[["warrior"]]}]}