{"basic":["死","Death","878"],"extended":[{"jlpt":["jlpt-n3"],"tags":["wanikani7"],"japanese":[{"word":"必死","reading":"ひっし"}],"senses":[["frantic","frenetic","desperate"],["inevitable death"],["brinkmate (inevitable checkmate)"]]},{"jlpt":["jlpt-n3","jlpt-n1"],"tags":["wanikani40"],"japanese":[{"word":"宜しく","reading":"よろしく"},{"word":"宜敷く","reading":"よろしく"}],"senses":[["well","properly","suitably"],["best regards","please remember me","please treat me favorably (favourably)","please take care of","please do"],["just like ...","as though one were ..."],["by all means","of course"]]},{"jlpt":["jlpt-n1"],"tags":[],"japanese":[{"word":"生死","reading":"せいし"},{"word":"生死","reading":"しょうし"},{"word":"生死","reading":"しょうじ"}],"senses":[["life and death"],["samsara (cycle of death and rebirth)"],["death"]]},{"jlpt":[],"tags":[],"japanese":[{"word":"戦死","reading":"せんし"}],"senses":[["death in battle"],["Killed in action"]]},{"jlpt":[],"tags":["wanikani18"],"japanese":[{"word":"脳死","reading":"のうし"}],"senses":[["brain death"],["Brain death"]]},{"jlpt":[],"tags":[],"japanese":[{"word":"水死","reading":"すいし"}],"senses":[["death by drowning"],["Drowning"]]},{"jlpt":[],"tags":["wanikani48"],"japanese":[{"word":"餓死","reading":"がし"},{"word":"餓死","reading":"がしん"}],"senses":[["(death from) starvation","starving to death"]]},{"jlpt":[],"tags":["wanikani16"],"japanese":[{"word":"急死","reading":"きゅうし"}],"senses":[["sudden death"]]},{"jlpt":[],"tags":[],"japanese":[{"word":"起死回生","reading":"きしかいせい"}],"senses":[["revival from the brink of death","recovering from a hopeless situation","resuscitation","revitalization"]]},{"jlpt":[],"tags":[],"japanese":[{"word":"焼死","reading":"しょうし"}],"senses":[["death by fire"]]},{"jlpt":[],"tags":["wanikani43"],"japanese":[{"word":"即死","reading":"そくし"}],"senses":[["instant death"]]},{"jlpt":[],"tags":[],"japanese":[{"word":"検視","reading":"けんし"},{"word":"検屍","reading":"けんし"},{"word":"検死","reading":"けんし"}],"senses":[["autopsy","inquest","investigation of death"],["Autopsy"]]},{"jlpt":[],"tags":[],"japanese":[{"word":"安楽死","reading":"あんらくし"}],"senses":[["euthanasia"],["Euthanasia"]]},{"jlpt":[],"tags":[],"japanese":[{"word":"切支丹","reading":"キリシタン"},{"word":"吉利支丹","reading":"キリシタン"},{"word":"切死丹","reading":"キリシタン"},{"word":"鬼理死丹","reading":"キリシタン"},{"word":"鬼利死丹","reading":"キリシタン"}],"senses":[["early Japanese Christianity (from the later Muromachi period)","early Japanese Christian"],["Kirishitan"]]},{"jlpt":[],"tags":[],"japanese":[{"word":"致死","reading":"ちし"}],"senses":[["lethal","fatal"]]},{"jlpt":[],"tags":[],"japanese":[{"word":"四死球","reading":"ししきゅう"}],"senses":[["bases on balls and pitches striking the batsmen"]]},{"jlpt":[],"tags":[],"japanese":[{"word":"二死","reading":"にし"}],"senses":[["two out","two down (and one to go)"]]},{"jlpt":[],"tags":[],"japanese":[{"word":"過失致死","reading":"かしつちし"}],"senses":[["involuntary manslaughter","accidental homicide","negligent homicide"]]},{"jlpt":[],"tags":[],"japanese":[{"word":"無死","reading":"むし"}],"senses":[["no outs"]]},{"jlpt":[],"tags":[],"japanese":[{"word":"病死","reading":"びょうし"}],"senses":[["death from disease","death from illness"]]},{"jlpt":["jlpt-n3"],"tags":["wanikani7"],"japanese":[{"word":"必死","reading":"ひっし"}],"senses":[["frantic","frenetic","desperate"],["inevitable death"],["brinkmate (inevitable checkmate)"]]},{"jlpt":["jlpt-n3","jlpt-n1"],"tags":["wanikani40"],"japanese":[{"word":"宜しく","reading":"よろしく"},{"word":"宜敷く","reading":"よろしく"}],"senses":[["well","properly","suitably"],["best regards","please remember me","please treat me favorably (favourably)","please take care of","please do"],["just like ...","as though one were ..."],["by all means","of course"]]},{"jlpt":["jlpt-n1"],"tags":[],"japanese":[{"word":"生死","reading":"せいし"},{"word":"生死","reading":"しょうし"},{"word":"生死","reading":"しょうじ"}],"senses":[["life and death"],["samsara (cycle of death and rebirth)"],["death"]]},{"jlpt":[],"tags":[],"japanese":[{"word":"戦死","reading":"せんし"}],"senses":[["death in battle"],["Killed in action"]]},{"jlpt":[],"tags":["wanikani18"],"japanese":[{"word":"脳死","reading":"のうし"}],"senses":[["brain death"],["Brain death"]]},{"jlpt":[],"tags":[],"japanese":[{"word":"水死","reading":"すいし"}],"senses":[["death by drowning"],["Drowning"]]},{"jlpt":[],"tags":["wanikani48"],"japanese":[{"word":"餓死","reading":"がし"},{"word":"餓死","reading":"がしん"}],"senses":[["(death from) starvation","starving to death"]]},{"jlpt":[],"tags":["wanikani16"],"japanese":[{"word":"急死","reading":"きゅうし"}],"senses":[["sudden death"]]},{"jlpt":[],"tags":[],"japanese":[{"word":"起死回生","reading":"きしかいせい"}],"senses":[["revival from the brink of death","recovering from a hopeless situation","resuscitation","revitalization"]]},{"jlpt":[],"tags":[],"japanese":[{"word":"焼死","reading":"しょうし"}],"senses":[["death by fire"]]},{"jlpt":[],"tags":["wanikani43"],"japanese":[{"word":"即死","reading":"そくし"}],"senses":[["instant death"]]},{"jlpt":[],"tags":[],"japanese":[{"word":"検視","reading":"けんし"},{"word":"検屍","reading":"けんし"},{"word":"検死","reading":"けんし"}],"senses":[["autopsy","inquest","investigation of death"],["Autopsy"]]},{"jlpt":[],"tags":[],"japanese":[{"word":"安楽死","reading":"あんらくし"}],"senses":[["euthanasia"],["Euthanasia"]]},{"jlpt":[],"tags":[],"japanese":[{"word":"切支丹","reading":"キリシタン"},{"word":"吉利支丹","reading":"キリシタン"},{"word":"切死丹","reading":"キリシタン"},{"word":"鬼理死丹","reading":"キリシタン"},{"word":"鬼利死丹","reading":"キリシタン"}],"senses":[["early Japanese Christianity (from the later Muromachi period)","early Japanese Christian"],["Kirishitan"]]},{"jlpt":[],"tags":[],"japanese":[{"word":"致死","reading":"ちし"}],"senses":[["lethal","fatal"]]},{"jlpt":[],"tags":[],"japanese":[{"word":"四死球","reading":"ししきゅう"}],"senses":[["bases on balls and pitches striking the batsmen"]]},{"jlpt":[],"tags":[],"japanese":[{"word":"二死","reading":"にし"}],"senses":[["two out","two down (and one to go)"]]},{"jlpt":[],"tags":[],"japanese":[{"word":"過失致死","reading":"かしつちし"}],"senses":[["involuntary manslaughter","accidental homicide","negligent homicide"]]},{"jlpt":[],"tags":[],"japanese":[{"word":"無死","reading":"むし"}],"senses":[["no outs"]]},{"jlpt":[],"tags":[],"japanese":[{"word":"病死","reading":"びょうし"}],"senses":[["death from disease","death from illness"]]},{"jlpt":[],"tags":[],"japanese":[{"word":"飢え死に","reading":"うえじに"},{"word":"飢え死に","reading":"かつえじに"},{"word":"餓え死に","reading":"うえじに"},{"word":"餓え死に","reading":"かつえじに"},{"word":"飢死に","reading":"うえじに"},{"word":"飢死に","reading":"かつえじに"},{"word":"飢え死","reading":"うえじに"},{"word":"飢え死","reading":"かつえじに"},{"word":"飢死","reading":"うえじに"},{"word":"飢死","reading":"かつえじに"},{"word":"饑死","reading":"うえじに"},{"word":"饑死","reading":"かつえじに"}],"senses":[["(death from) starvation","starving to death"]]},{"jlpt":[],"tags":[],"japanese":[{"word":"必死になって","reading":"ひっしになって"}],"senses":[["desperately","for one's dear life"]]}]}