{"basic":["澄","Lucidity","1839"],"extended":[{"jlpt":["jlpt-n2"],"tags":["wanikani45"],"japanese":[{"word":"澄む","reading":"すむ"},{"word":"清む","reading":"すむ"}],"senses":[["to become clear (water, air, etc.)","to become transparent"],["to resonate clearly (e.g. voice)"],["to become serene","to become tranquil","to be free of worries"],["to pronounce as an unvoiced sound"]]},{"jlpt":["jlpt-n2"],"tags":["wanikani45"],"japanese":[{"word":"澄む","reading":"すむ"},{"word":"清む","reading":"すむ"}],"senses":[["to become clear (water, air, etc.)","to become transparent"],["to resonate clearly (e.g. voice)"],["to become serene","to become tranquil","to be free of worries"],["to pronounce as an unvoiced sound"]]}]}