{"basic":["突","Stab","1416"],"extended":[{"jlpt":["jlpt-n3"],"tags":["wanikani40"],"japanese":[{"word":"衝突","reading":"しょうとつ"}],"senses":[["collision","crash","running into"],["conflict","quarrel","clashing"],["Collision"]]},{"jlpt":["jlpt-n2"],"tags":[],"japanese":[{"word":"煙突","reading":"えんとつ"},{"word":"烟突","reading":"えんとつ"}],"senses":[["chimney","smokestack","funnel (of a ship)","stovepipe"],["carrying a passenger without turning on the taximeter"],["Chimney"]]},{"jlpt":["jlpt-n3"],"tags":["wanikani26"],"japanese":[{"word":"突然","reading":"とつぜん"}],"senses":[["abrupt","sudden","unexpected"]]},{"jlpt":["jlpt-n5"],"tags":[],"japanese":[{"word":"米","reading":"メートル"},{"word":"米突","reading":"メートル"}],"senses":[["metre","meter"],["meter","gauge"],["Rice"]]},{"jlpt":["jlpt-n2"],"tags":["wanikani26"],"japanese":[{"word":"突く","reading":"つく"},{"word":"衝く","reading":"つく"},{"word":"撞く","reading":"つく"},{"word":"捺く","reading":"つく"}],"senses":[["to prick","to stab"],["to poke","to prod","to push","to thrust","to nudge","to hit","to strike"],["to use (a cane)","to prop oneself up with","to press against (the floor, etc.)"],["to attack"],["to brave (the rain, etc.)"]]},{"jlpt":["jlpt-n2"],"tags":[],"japanese":[{"word":"突っ込む","reading":"つっこむ"},{"word":"突っこむ","reading":"つっこむ"},{"word":"突込む","reading":"つっこむ"}],"senses":[["to thrust (something) into (something)","to cram","to stuff","to shove"],["to plunge into","to charge into","to rush into","to ram into","to crash into"],["to delve into (a matter)","to go into depth","to get to the heart (of something)"],["to press (someone) about","to point out (e.g. an inconsistency)","to question sharply","to grill"],["to get involved with","to meddle in","to poke one's nose into"],["to riposte","to retort","to quip"]]},{"jlpt":["jlpt-n2"],"tags":[],"japanese":[{"word":"突き当たる","reading":"つきあたる"},{"word":"突き当る","reading":"つきあたる"},{"word":"衝き当たる","reading":"つきあたる"},{"word":"衝き当る","reading":"つきあたる"}],"senses":[["to run into","to collide with","to crash into","to bump against"],["to come to the end of (a street)"],["to run into (difficulties, problems, etc.)","to run up against"]]},{"jlpt":["jlpt-n2"],"tags":[],"japanese":[{"word":"突き当たり","reading":"つきあたり"},{"word":"突き当り","reading":"つきあたり"},{"word":"突当り","reading":"つきあたり"},{"word":"突きあたり","reading":"つきあたり"},{"word":"つき当たり","reading":"つきあたり"},{"word":"突当たり","reading":"つきあたり"}],"senses":[["end (of a street, hallway, etc.)"]]},{"jlpt":["jlpt-n1"],"tags":[],"japanese":[{"word":"突破","reading":"とっぱ"}],"senses":[["breaking through","breakthrough","penetration"],["surmounting","overcoming"],["exceeding","passing"]]},{"jlpt":["jlpt-n1"],"tags":["wanikani47"],"japanese":[{"word":"突如","reading":"とつじょ"}],"senses":[["suddenly","all of a sudden"]]},{"jlpt":[],"tags":[],"japanese":[{"word":"突入","reading":"とつにゅう"}],"senses":[["rushing into","breaking into","storming"],["plunging into (war, etc.)","embarking on (a new venture)"]]},{"jlpt":[],"tags":[],"japanese":[{"word":"激突","reading":"げきとつ"}],"senses":[["crash into","clash"]]},{"jlpt":[],"tags":[],"japanese":[{"word":"突進","reading":"とっしん"}],"senses":[["rush","charge"]]},{"jlpt":[],"tags":["wanikani50"],"japanese":[{"word":"唐突","reading":"とうとつ"}],"senses":[["abrupt","sudden"]]},{"jlpt":["jlpt-n1"],"tags":[],"japanese":[{"word":"突く","reading":"つつく"},{"word":"突付く","reading":"つつく"},{"word":"突つく","reading":"つつく"}],"senses":[["to poke (repeatedly, lightly)","to nudge"],["to peck at (one's food)","to pick at"],["to peck at (someone's faults, etc.)"],["to egg on","to put up to"]]},{"jlpt":[],"tags":[],"japanese":[{"word":"突き刺す","reading":"つきさす"},{"word":"突きさす","reading":"つきさす"},{"word":"突刺す","reading":"つきさす"},{"word":"つき刺す","reading":"つきさす"}],"senses":[["to stab","to pierce","to thrust"]]},{"jlpt":[],"tags":[],"japanese":[{"word":"追突","reading":"ついとつ"}],"senses":[["rear-end collision"]]},{"jlpt":[],"tags":[],"japanese":[{"word":"突き抜ける","reading":"つきぬける"},{"word":"突抜ける","reading":"つきぬける"}],"senses":[["to pierce through","to break through"]]},{"jlpt":[],"tags":[],"japanese":[{"word":"楯突く","reading":"たてつく"},{"word":"盾突く","reading":"たてつく"},{"word":"たて突く","reading":"たてつく"},{"word":"盾つく","reading":"たてつく"},{"word":"楯つく","reading":"たてつく"}],"senses":[["to defy","to disobey","to rebel against","to oppose","to resist"]]},{"jlpt":["jlpt-n1"],"tags":[],"japanese":[{"word":"突っ張る","reading":"つっぱる"}],"senses":[["to cramp up","to tighten","to stiffen"],["to be insistent","to persist (in one's opinion)","to stick to one's guns"],["to act tough","to bluff","to be defiant","to be unruly"],["to prop up (e.g. with a post)","to support"],["to push out (one's legs or arms)","to stretch (e.g. an arm against the wall)","to press"],["to thrust (one's opponent)"]]},{"jlpt":["jlpt-n3"],"tags":["wanikani40"],"japanese":[{"word":"衝突","reading":"しょうとつ"}],"senses":[["collision","crash","running into"],["conflict","quarrel","clashing"],["Collision"]]},{"jlpt":["jlpt-n2"],"tags":[],"japanese":[{"word":"煙突","reading":"えんとつ"},{"word":"烟突","reading":"えんとつ"}],"senses":[["chimney","smokestack","funnel (of a ship)","stovepipe"],["carrying a passenger without turning on the taximeter"],["Chimney"]]},{"jlpt":["jlpt-n3"],"tags":["wanikani26"],"japanese":[{"word":"突然","reading":"とつぜん"}],"senses":[["abrupt","sudden","unexpected"]]},{"jlpt":["jlpt-n5"],"tags":[],"japanese":[{"word":"米","reading":"メートル"},{"word":"米突","reading":"メートル"}],"senses":[["metre","meter"],["meter","gauge"],["Rice"]]},{"jlpt":["jlpt-n2"],"tags":["wanikani26"],"japanese":[{"word":"突く","reading":"つく"},{"word":"衝く","reading":"つく"},{"word":"撞く","reading":"つく"},{"word":"捺く","reading":"つく"}],"senses":[["to prick","to stab"],["to poke","to prod","to push","to thrust","to nudge","to hit","to strike"],["to use (a cane)","to prop oneself up with","to press against (the floor, etc.)"],["to attack"],["to brave (the rain, etc.)"]]},{"jlpt":["jlpt-n2"],"tags":[],"japanese":[{"word":"突っ込む","reading":"つっこむ"},{"word":"突っこむ","reading":"つっこむ"},{"word":"突込む","reading":"つっこむ"}],"senses":[["to thrust (something) into (something)","to cram","to stuff","to shove"],["to plunge into","to charge into","to rush into","to ram into","to crash into"],["to delve into (a matter)","to go into depth","to get to the heart (of something)"],["to press (someone) about","to point out (e.g. an inconsistency)","to question sharply","to grill"],["to get involved with","to meddle in","to poke one's nose into"],["to riposte","to retort","to quip"]]},{"jlpt":["jlpt-n2"],"tags":[],"japanese":[{"word":"突き当たる","reading":"つきあたる"},{"word":"突き当る","reading":"つきあたる"},{"word":"衝き当たる","reading":"つきあたる"},{"word":"衝き当る","reading":"つきあたる"}],"senses":[["to run into","to collide with","to crash into","to bump against"],["to come to the end of (a street)"],["to run into (difficulties, problems, etc.)","to run up against"]]},{"jlpt":["jlpt-n2"],"tags":[],"japanese":[{"word":"突き当たり","reading":"つきあたり"},{"word":"突き当り","reading":"つきあたり"},{"word":"突当り","reading":"つきあたり"},{"word":"突きあたり","reading":"つきあたり"},{"word":"つき当たり","reading":"つきあたり"},{"word":"突当たり","reading":"つきあたり"}],"senses":[["end (of a street, hallway, etc.)"]]},{"jlpt":["jlpt-n1"],"tags":[],"japanese":[{"word":"突破","reading":"とっぱ"}],"senses":[["breaking through","breakthrough","penetration"],["surmounting","overcoming"],["exceeding","passing"]]},{"jlpt":["jlpt-n1"],"tags":["wanikani47"],"japanese":[{"word":"突如","reading":"とつじょ"}],"senses":[["suddenly","all of a sudden"]]},{"jlpt":[],"tags":[],"japanese":[{"word":"突入","reading":"とつにゅう"}],"senses":[["rushing into","breaking into","storming"],["plunging into (war, etc.)","embarking on (a new venture)"]]},{"jlpt":[],"tags":[],"japanese":[{"word":"激突","reading":"げきとつ"}],"senses":[["crash into","clash"]]},{"jlpt":[],"tags":[],"japanese":[{"word":"突進","reading":"とっしん"}],"senses":[["rush","charge"]]},{"jlpt":[],"tags":["wanikani50"],"japanese":[{"word":"唐突","reading":"とうとつ"}],"senses":[["abrupt","sudden"]]},{"jlpt":["jlpt-n1"],"tags":[],"japanese":[{"word":"突く","reading":"つつく"},{"word":"突付く","reading":"つつく"},{"word":"突つく","reading":"つつく"}],"senses":[["to poke (repeatedly, lightly)","to nudge"],["to peck at (one's food)","to pick at"],["to peck at (someone's faults, etc.)"],["to egg on","to put up to"]]},{"jlpt":[],"tags":[],"japanese":[{"word":"突き刺す","reading":"つきさす"},{"word":"突きさす","reading":"つきさす"},{"word":"突刺す","reading":"つきさす"},{"word":"つき刺す","reading":"つきさす"}],"senses":[["to stab","to pierce","to thrust"]]},{"jlpt":[],"tags":[],"japanese":[{"word":"追突","reading":"ついとつ"}],"senses":[["rear-end collision"]]},{"jlpt":[],"tags":[],"japanese":[{"word":"突き抜ける","reading":"つきぬける"},{"word":"突抜ける","reading":"つきぬける"}],"senses":[["to pierce through","to break through"]]},{"jlpt":[],"tags":[],"japanese":[{"word":"楯突く","reading":"たてつく"},{"word":"盾突く","reading":"たてつく"},{"word":"たて突く","reading":"たてつく"},{"word":"盾つく","reading":"たてつく"},{"word":"楯つく","reading":"たてつく"}],"senses":[["to defy","to disobey","to rebel against","to oppose","to resist"]]},{"jlpt":["jlpt-n1"],"tags":[],"japanese":[{"word":"突っ張る","reading":"つっぱる"}],"senses":[["to cramp up","to tighten","to stiffen"],["to be insistent","to persist (in one's opinion)","to stick to one's guns"],["to act tough","to bluff","to be defiant","to be unruly"],["to prop up (e.g. with a post)","to support"],["to push out (one's legs or arms)","to stretch (e.g. an arm against the wall)","to press"],["to thrust (one's opponent)"]]},{"jlpt":[],"tags":[],"japanese":[{"word":"突き","reading":"つき"}],"senses":[["thrust","stab","lunge","pass (in fencing)"],["tsuki","thrust to the throat (in kendo)"],["tsuki","thrust to the chest"]]},{"jlpt":[],"tags":[],"japanese":[{"word":"突っかける","reading":"つっかける"},{"word":"突っ掛ける","reading":"つっかける"},{"word":"突掛ける","reading":"つっかける"}],"senses":[["to slip on (slippers, sandals, etc.)"],["to hit (e.g. one's leg) against","to bash into"],["to push (one's opponent) down before he stands up"]]},{"jlpt":[],"tags":[],"japanese":[{"word":"突っ張り","reading":"つっぱり"},{"word":"突張り","reading":"つっぱり"}],"senses":[["prop","strut","support","brace","bar"],["becoming taut","tightness","stiffness","cramp"],["thrust","slapping attacks"],["(juvenile) delinquent","punk"]]},{"jlpt":[],"tags":[],"japanese":[{"word":"突き上げる","reading":"つきあげる"},{"word":"突上げる","reading":"つきあげる"},{"word":"衝き上げる","reading":"つきあげる"}],"senses":[["to push up","to force up","to toss"],["to pressure one's superiors"],["to burst out (of emotions, etc.)","to fill one's heart"]]},{"jlpt":[],"tags":[],"japanese":[{"word":"突出","reading":"とっしゅつ"}],"senses":[["projection","protrusion"]]},{"jlpt":[],"tags":[],"japanese":[{"word":"突起","reading":"とっき"}],"senses":[["protuberance","projection","prominence","bump","boss","process","apophysis"]]},{"jlpt":[],"tags":[],"japanese":[{"word":"突風","reading":"とっぷう"}],"senses":[["gust (of wind)","blast"]]},{"jlpt":[],"tags":[],"japanese":[{"word":"突尼斯","reading":"チュニジア"},{"word":"突尼斯","reading":"テュニジア"}],"senses":[["Tunisia"]]}]}