{"basic":["答","Solution","1018"],"extended":[{"jlpt":["jlpt-n2"],"tags":[],"japanese":[{"word":"解答","reading":"かいとう"}],"senses":[["answer","solution"]]},{"jlpt":["jlpt-n2"],"tags":[],"japanese":[{"word":"回答","reading":"かいとう"}],"senses":[["reply","answer"]]},{"jlpt":["jlpt-n1"],"tags":[],"japanese":[{"word":"返答","reading":"へんとう"}],"senses":[["reply","answer"]]},{"jlpt":[],"tags":[],"japanese":[{"word":"応答","reading":"おうとう"}],"senses":[["reply","answer","response"]]},{"jlpt":[],"tags":[],"japanese":[{"word":"口答え","reading":"くちごたえ"},{"word":"口ごたえ","reading":"くちごたえ"},{"word":"口応え","reading":"くちごたえ"}],"senses":[["retort","back talk","backchat"]]},{"jlpt":[],"tags":[],"japanese":[{"word":"押し問答","reading":"おしもんどう"},{"word":"押問答","reading":"おしもんどう"}],"senses":[["arguing back and forth","bandying words","verbal tug-of-war"]]},{"jlpt":["jlpt-n2"],"tags":[],"japanese":[{"word":"問答","reading":"もんどう"}],"senses":[["questions and answers","dialogue"]]},{"jlpt":[],"tags":[],"japanese":[{"word":"贈答","reading":"ぞうとう"}],"senses":[["exchange of presents"]]},{"jlpt":[],"tags":[],"japanese":[{"word":"手応え","reading":"てごたえ"},{"word":"手ごたえ","reading":"てごたえ"},{"word":"手答え","reading":"てごたえ"}],"senses":[["response (felt in the hands)","resistance"],["reaction","response","effect"]]},{"jlpt":[],"tags":[],"japanese":[{"word":"加答児","reading":"カタル"}],"senses":[["catarrh"]]},{"jlpt":["jlpt-n2"],"tags":[],"japanese":[{"word":"解答","reading":"かいとう"}],"senses":[["answer","solution"]]},{"jlpt":["jlpt-n2"],"tags":[],"japanese":[{"word":"回答","reading":"かいとう"}],"senses":[["reply","answer"]]},{"jlpt":["jlpt-n1"],"tags":[],"japanese":[{"word":"返答","reading":"へんとう"}],"senses":[["reply","answer"]]},{"jlpt":[],"tags":[],"japanese":[{"word":"応答","reading":"おうとう"}],"senses":[["reply","answer","response"]]},{"jlpt":[],"tags":[],"japanese":[{"word":"口答え","reading":"くちごたえ"},{"word":"口ごたえ","reading":"くちごたえ"},{"word":"口応え","reading":"くちごたえ"}],"senses":[["retort","back talk","backchat"]]},{"jlpt":[],"tags":[],"japanese":[{"word":"押し問答","reading":"おしもんどう"},{"word":"押問答","reading":"おしもんどう"}],"senses":[["arguing back and forth","bandying words","verbal tug-of-war"]]},{"jlpt":["jlpt-n2"],"tags":[],"japanese":[{"word":"問答","reading":"もんどう"}],"senses":[["questions and answers","dialogue"]]},{"jlpt":[],"tags":[],"japanese":[{"word":"贈答","reading":"ぞうとう"}],"senses":[["exchange of presents"]]},{"jlpt":[],"tags":[],"japanese":[{"word":"手応え","reading":"てごたえ"},{"word":"手ごたえ","reading":"てごたえ"},{"word":"手答え","reading":"てごたえ"}],"senses":[["response (felt in the hands)","resistance"],["reaction","response","effect"]]},{"jlpt":[],"tags":[],"japanese":[{"word":"加答児","reading":"カタル"}],"senses":[["catarrh"]]}]}