{"basic":["粒","Grains","990"],"extended":[{"jlpt":["jlpt-n2"],"tags":["wanikani44"],"japanese":[{"word":"粒","reading":"つぶ"},{"word":"粒","reading":"りゅう"},{"word":"粒","reading":"つび"},{"word":"粒","reading":"つぼ"}],"senses":[["grain","bead","drop"],["counter for small round objects including grains, seeds, pills, drops"]]},{"jlpt":[],"tags":["wanikani44"],"japanese":[{"word":"粒子","reading":"りゅうし"}],"senses":[["particle","grain"]]},{"jlpt":[],"tags":[],"japanese":[{"word":"大粒","reading":"おおつぶ"}],"senses":[["large drop (rain, sweat, tears, etc.)","large grain-like object (grape, cherry, etc.)"]]},{"jlpt":["jlpt-n2"],"tags":["wanikani44"],"japanese":[{"word":"粒","reading":"つぶ"},{"word":"粒","reading":"りゅう"},{"word":"粒","reading":"つび"},{"word":"粒","reading":"つぼ"}],"senses":[["grain","bead","drop"],["counter for small round objects including grains, seeds, pills, drops"]]},{"jlpt":[],"tags":["wanikani44"],"japanese":[{"word":"粒子","reading":"りゅうし"}],"senses":[["particle","grain"]]},{"jlpt":[],"tags":[],"japanese":[{"word":"大粒","reading":"おおつぶ"}],"senses":[["large drop (rain, sweat, tears, etc.)","large grain-like object (grape, cherry, etc.)"]]}]}