{"basic":["紅","Crimson","1455"],"extended":[{"jlpt":["jlpt-n5"],"tags":["wanikani4"],"japanese":[{"word":"赤","reading":"あか"},{"word":"紅","reading":"あか"},{"word":"朱","reading":"あか"},{"word":"緋","reading":"あか"}],"senses":[["red","crimson","scarlet"],["red-containing colour (e.g. brown, pink, orange)"],["Red (i.e. communist)"],["red light (traffic)"],["red ink (i.e. in finance or proof-reading)","(in) the red"],["complete","total","perfect","obvious"],["copper"],["red 5-point card"],["Aka"],["Red"]]},{"jlpt":["jlpt-n5"],"tags":["wanikani34"],"japanese":[{"word":"紅茶","reading":"こうちゃ"}],"senses":[["black tea"],["Black tea"]]},{"jlpt":["jlpt-n5"],"tags":["wanikani4"],"japanese":[{"word":"赤い","reading":"あかい"},{"word":"紅い","reading":"あかい"},{"word":"朱い","reading":"あかい"},{"word":"緋い","reading":"あかい"},{"word":"赭い","reading":"あかい"},{"word":"丹い","reading":"あかい"}],"senses":[["red","crimson","scarlet","vermilion","vermillion"],["Red","communist"],["beautiful"]]},{"jlpt":["jlpt-n2"],"tags":[],"japanese":[{"word":"紅葉","reading":"こうよう"},{"word":"黄葉","reading":"こうよう"},{"word":"紅葉","reading":"もみじ"},{"word":"黄葉","reading":"もみじ"},{"word":"椛","reading":"もみじ"}],"senses":[["autumn colours","fall colors","leaves changing color (colour)"],["leaves turning red","red leaves"],["leaves turning yellow","yellow leaves"],["(Japanese) maple (Acer japonicum)"],["venison"],["layered colors in garments, resembling autumn colors"],["Autumn leaf color"]]},{"jlpt":["jlpt-n2"],"tags":["wanikani36"],"japanese":[{"word":"口紅","reading":"くちべに"}],"senses":[["lipstick"],["Lipstick"]]},{"jlpt":[],"tags":[],"japanese":[{"word":"紅白","reading":"こうはく"}],"senses":[["red and white","colours for festive or auspicious occasions (colors)"],["two teams","two groups"],["Red and White singing contest","annual contest between male and female popular singers on New Year's Eve (sponsored and broadcast by NHK)"],["Kōhaku maku"]]},{"jlpt":[],"tags":[],"japanese":[{"word":"紅潮","reading":"こうちょう"}],"senses":[["flush","blush"]]},{"jlpt":[],"tags":["wanikani34"],"japanese":[{"word":"紅","reading":"くれない"},{"word":"紅","reading":"べに"},{"word":"紅","reading":"こう"}],"senses":[["deep red","crimson"],["rouge","lipstick"],["Kurenai"]]}]}