{"basic":["背","Stature","481"],"extended":[{"jlpt":["jlpt-n5"],"tags":["wanikani32"],"japanese":[{"word":"背広","reading":"せびろ"},{"word":"脊広","reading":"せびろ"},{"reading":"セビロ"}],"senses":[["business suit"],["Suit (clothing)"]]},{"jlpt":["jlpt-n4"],"tags":["wanikani32"],"japanese":[{"word":"背中","reading":"せなか"},{"word":"背なか","reading":"せなか"}],"senses":[["back (of body)"],["Human back"]]},{"jlpt":["jlpt-n5"],"tags":["wanikani30"],"japanese":[{"word":"背","reading":"せ"},{"word":"脊","reading":"せ"}],"senses":[["back","spine"],["reverse","rear side"],["height","stature"],["ridge (of a mountain)"]]},{"jlpt":["jlpt-n2","jlpt-n1"],"tags":[],"japanese":[{"word":"背負う","reading":"せおう"},{"word":"背負う","reading":"しょう"},{"word":"脊負う","reading":"せおう"},{"word":"脊負う","reading":"しょう"}],"senses":[["to carry on one's back"],["to be burdened with","to take responsibility for"],["to have (something) in the background","to be in front (of something)"],["to be conceited","to think highly of oneself"]]},{"jlpt":["jlpt-n1"],"tags":["wanikani30"],"japanese":[{"word":"背景","reading":"はいけい"}],"senses":[["background","scenery","backdrop","setting"],["background (of an incident, situation, etc.)","circumstances","context"],["backing","support (from behind the scenes)"]]},{"jlpt":["jlpt-n1"],"tags":["wanikani30"],"japanese":[{"word":"背後","reading":"はいご"}],"senses":[["back","rear"],["background","behind the scenes"]]},{"jlpt":["jlpt-n1"],"tags":[],"japanese":[{"word":"背く","reading":"そむく"},{"word":"叛く","reading":"そむく"}],"senses":[["to run counter to","to go against","to disobey","to infringe"]]},{"jlpt":[],"tags":[],"japanese":[{"word":"背泳ぎ","reading":"せおよぎ"}],"senses":[["backstroke (swimming)"],["Backstroke"]]},{"jlpt":[],"tags":[],"japanese":[{"word":"背番号","reading":"せばんごう"}],"senses":[["number on back of player's shirt","uniform number","shirt number"],["Number (sports)"]]},{"jlpt":[],"tags":[],"japanese":[{"word":"猫背","reading":"ねこぜ"}],"senses":[["bent back","hunchback","stoop"],["Kyphosis"]]},{"jlpt":["jlpt-n3"],"tags":[],"japanese":[{"word":"背","reading":"せい"},{"word":"脊","reading":"せい"}],"senses":[["height","stature"]]},{"jlpt":[],"tags":[],"japanese":[{"word":"背筋","reading":"せすじ"}],"senses":[["spine","line of the backbone"],["seam down the back (of clothing)"]]},{"jlpt":[],"tags":[],"japanese":[{"word":"背骨","reading":"せぼね"},{"word":"脊骨","reading":"せぼね"},{"word":"背ぼね","reading":"せぼね"}],"senses":[["spine","backbone","spinal column"]]},{"jlpt":[],"tags":[],"japanese":[{"word":"背信","reading":"はいしん"}],"senses":[["betrayal","infidelity"]]},{"jlpt":[],"tags":[],"japanese":[{"word":"背任","reading":"はいにん"}],"senses":[["breach of trust","malfeasance","malpractice","misappropriation"]]}]}