{"basic":["臓","Entrails","914"],"extended":[{"jlpt":["jlpt-n3"],"tags":["wanikani34"],"japanese":[{"word":"心臓","reading":"しんぞう"}],"senses":[["heart"],["guts","nerve","cheek","gall","spine"],["central part"],["Heart"]]},{"jlpt":["jlpt-n1"],"tags":["wanikani34"],"japanese":[{"word":"内臓","reading":"ないぞう"}],"senses":[["internal organs","intestines","viscera"]]},{"jlpt":[],"tags":["wanikani42"],"japanese":[{"word":"肝臓","reading":"かんぞう"}],"senses":[["liver"],["Liver"]]},{"jlpt":[],"tags":[],"japanese":[{"word":"腎臓","reading":"じんぞう"}],"senses":[["kidney"],["Kidney"]]},{"jlpt":[],"tags":[],"japanese":[{"word":"心臓病","reading":"しんぞうびょう"}],"senses":[["heart trouble","heart disease"]]},{"jlpt":["jlpt-n3"],"tags":["wanikani34"],"japanese":[{"word":"心臓","reading":"しんぞう"}],"senses":[["heart"],["guts","nerve","cheek","gall","spine"],["central part"],["Heart"]]},{"jlpt":["jlpt-n1"],"tags":["wanikani34"],"japanese":[{"word":"内臓","reading":"ないぞう"}],"senses":[["internal organs","intestines","viscera"]]},{"jlpt":[],"tags":["wanikani42"],"japanese":[{"word":"肝臓","reading":"かんぞう"}],"senses":[["liver"],["Liver"]]},{"jlpt":[],"tags":[],"japanese":[{"word":"腎臓","reading":"じんぞう"}],"senses":[["kidney"],["Kidney"]]},{"jlpt":[],"tags":[],"japanese":[{"word":"心臓病","reading":"しんぞうびょう"}],"senses":[["heart trouble","heart disease"]]}]}