{"basic":["衛","Defense","1775"],"extended":[{"jlpt":["jlpt-n3"],"tags":["wanikani32"],"japanese":[{"word":"衛星","reading":"えいせい"}],"senses":[["(natural) satellite","moon"],["(artificial) satellite"],["Natural satellite"]]},{"jlpt":["jlpt-n1"],"tags":["wanikani32"],"japanese":[{"word":"衛生","reading":"えいせい"}],"senses":[["hygiene","sanitation","health"],["Hygiene"]]},{"jlpt":["jlpt-n1"],"tags":[],"japanese":[{"word":"防衛","reading":"ぼうえい"}],"senses":[["defense","defence","protection"]]},{"jlpt":["jlpt-n1"],"tags":[],"japanese":[{"word":"護衛","reading":"ごえい"}],"senses":[["guard","convoy","escort"]]},{"jlpt":["jlpt-n1"],"tags":[],"japanese":[{"word":"守衛","reading":"しゅえい"}],"senses":[["security guard","doorkeeper"]]},{"jlpt":[],"tags":[],"japanese":[{"word":"人工衛星","reading":"じんこうえいせい"}],"senses":[["artificial satellite","man-made satellite"],["Satellite"]]},{"jlpt":[],"tags":[],"japanese":[{"word":"自衛隊","reading":"じえいたい"}],"senses":[["self-defence force","self-defense force"],["Japan Self-Defense Force","JSDF"],["Japan Self-Defense Forces"]]},{"jlpt":[],"tags":[],"japanese":[{"word":"海上自衛隊","reading":"かいじょうじえいたい"}],"senses":[["Maritime Self Defense Forces (Defence)"],["Japan Maritime Self-Defense Force"]]},{"jlpt":[],"tags":[],"japanese":[{"word":"正当防衛","reading":"せいとうぼうえい"}],"senses":[["legitimate self-defence","legitimate self-defense"],["Right of self-defense"]]},{"jlpt":[],"tags":[],"japanese":[{"word":"通信衛星","reading":"つうしんえいせい"}],"senses":[["communication satellite","Broadcast Satellite","BS"],["Communications satellite"]]},{"jlpt":[],"tags":[],"japanese":[{"word":"歯科衛生士","reading":"しかえいせいし"}],"senses":[["dental hygienist"],["Dental hygienist"]]},{"jlpt":[],"tags":[],"japanese":[{"word":"防衛庁","reading":"ぼうえいちょう"}],"senses":[["Japan Defense Agency (became Ministry of Defense in January 2007)"],["Boueichou"]]},{"jlpt":[],"tags":[],"japanese":[{"word":"行方","reading":"ゆくえ"},{"word":"行衛","reading":"ゆくえ"}],"senses":[["(one's) whereabouts"],["destination","where one is headed"],["outcome","course (of events)","development","direction","tide"],["future","journey ahead"]]},{"jlpt":[],"tags":[],"japanese":[{"word":"前衛","reading":"ぜんえい"}],"senses":[["advance guard","vanguard"],["avant-garde (e.g. music)"]]},{"jlpt":[],"tags":[],"japanese":[{"word":"衛生的","reading":"えいせいてき"}],"senses":[["hygienic","sanitary"]]},{"jlpt":["jlpt-n2"],"tags":["wanikani32"],"japanese":[{"word":"自衛","reading":"じえい"}],"senses":[["self-defense","self-defence"]]},{"jlpt":[],"tags":[],"japanese":[{"word":"航空自衛隊","reading":"こうくうじえいたい"}],"senses":[["Japan Air Self-Defense Force","JASDF"],["Air Self-Defense Force","ASDF"],["Japan Air Self-Defense Force"]]},{"jlpt":[],"tags":[],"japanese":[{"word":"公衆衛生","reading":"こうしゅうえいせい"}],"senses":[["sanitation","public health"],["Public health"]]},{"jlpt":[],"tags":[],"japanese":[{"word":"陸上自衛隊","reading":"りくじょうじえいたい"}],"senses":[["Japan Ground Self-Defense Force","JGSDF"],["Japan Ground Self-Defense Force"]]},{"jlpt":[],"tags":[],"japanese":[{"word":"近衛","reading":"このえ"}],"senses":[["Imperial Guards"],["Konoe"]]},{"jlpt":[],"tags":[],"japanese":[{"word":"親衛","reading":"しんえい"}],"senses":[["monarch's guards"]]},{"jlpt":[],"tags":[],"japanese":[{"word":"専守防衛","reading":"せんしゅぼうえい"}],"senses":[["nonaggressive defense (policy) (defence)"]]},{"jlpt":[],"tags":[],"japanese":[{"word":"自衛官","reading":"じえいかん"}],"senses":[["Japanese Self-Defense Force official","Self-Defense Force official"]]},{"jlpt":[],"tags":[],"japanese":[{"word":"防衛施設庁","reading":"ぼうえいしせつちょう"}],"senses":[["(Japanese) Defense Facilities Administration Agency (Defence)"]]}]}