{"basic":["負","Defeat","67"],"extended":[{"jlpt":["jlpt-n1"],"tags":[],"japanese":[{"word":"負債","reading":"ふさい"}],"senses":[["debt","liabilities"],["Liability (financial accounting)"]]},{"jlpt":["jlpt-n4"],"tags":["wanikani9"],"japanese":[{"word":"負ける","reading":"まける"},{"word":"敗ける","reading":"まける"},{"word":"敗北る","reading":"まける"}],"senses":[["to lose","to be defeated"],["to succumb","to give in","to surrender","to yield"],["to be inferior to"],["to break out in a rash due to (e.g. lacquer, shaving, etc.)"],["to reduce the price","to give a discount","to throw in (something extra) for free"]]},{"jlpt":["jlpt-n3"],"tags":[],"japanese":[{"word":"負け","reading":"まけ"}],"senses":[["defeat","loss","losing (a game)"],["failing to live up to (one's name, looks, etc.)"],["discount","loss (on a sale)"]]},{"jlpt":["jlpt-n2"],"tags":["wanikani9"],"japanese":[{"word":"勝負","reading":"しょうぶ"}],"senses":[["victory or defeat"],["match","contest","game","bout"],["Shoubu"]]},{"jlpt":["jlpt-n2","jlpt-n1"],"tags":[],"japanese":[{"word":"背負う","reading":"せおう"},{"word":"背負う","reading":"しょう"},{"word":"脊負う","reading":"せおう"},{"word":"脊負う","reading":"しょう"}],"senses":[["to carry on one's back"],["to be burdened with","to take responsibility for"],["to have (something) in the background","to be in front (of something)"],["to be conceited","to think highly of oneself"]]},{"jlpt":["jlpt-n1"],"tags":[],"japanese":[{"word":"負う","reading":"おう"}],"senses":[["to bear","to carry on one's back"],["to take responsibility for","to accept a duty"],["to receive (wound)","to incur (damage)","to be injured"],["to owe"]]},{"jlpt":["jlpt-n1"],"tags":[],"japanese":[{"word":"負傷","reading":"ふしょう"}],"senses":[["injury","wound"]]},{"jlpt":["jlpt-n1"],"tags":["wanikani24"],"japanese":[{"word":"負担","reading":"ふたん"}],"senses":[["burden","load","responsibility"],["bearing (a cost, responsibility, etc.)","shouldering"]]},{"jlpt":["jlpt-n1"],"tags":[],"japanese":[{"word":"負かす","reading":"まかす"}],"senses":[["to defeat"]]},{"jlpt":["jlpt-n1"],"tags":[],"japanese":[{"word":"お負け","reading":"おまけ"},{"word":"御負け","reading":"おまけ"}],"senses":[["freebie (e.g. with a purchase)","something additional","bonus","an extra"],["price reduction","discount"],["exaggeration"]]},{"jlpt":[],"tags":[],"japanese":[{"word":"負荷","reading":"ふか"}],"senses":[["burden","load (e.g. CPU time, electricity, etc.)"],["Load"]]},{"jlpt":[],"tags":[],"japanese":[{"word":"贔屓","reading":"ひいき"},{"word":"贔負","reading":"ひいき"}],"senses":[["favour","favor","patronage","favouritism","favoritism","partiality"],["favourite","favorite"],["patron","supporter","backer"],["Bixi (tortoise)"]]},{"jlpt":[],"tags":[],"japanese":[{"word":"顔負け","reading":"かおまけ"}],"senses":[["being put to shame","being outshone","being eclipsed","feeling embarrassed"]]},{"jlpt":[],"tags":[],"japanese":[{"word":"請け負う","reading":"うけおう"},{"word":"請負う","reading":"うけおう"}],"senses":[["to contract","to undertake"],["to take over","to take responsibility for"]]},{"jlpt":[],"tags":[],"japanese":[{"word":"抱負","reading":"ほうふ"}],"senses":[["aspiration","ambition","plan","hopes","wishes"]]},{"jlpt":[],"tags":[],"japanese":[{"word":"勝ち負け","reading":"かちまけ"}],"senses":[["victory or defeat","victory and defeat"]]},{"jlpt":[],"tags":[],"japanese":[{"word":"負","reading":"ふ"}],"senses":[["negative","minus"]]},{"jlpt":[],"tags":[],"japanese":[{"word":"自負","reading":"じふ"}],"senses":[["pride","self-confidence","thinking highly of oneself","being proud of one's abilities or achievements"]]},{"jlpt":[],"tags":[],"japanese":[{"word":"負んぶ","reading":"おんぶ"}],"senses":[["carrying on one's back (e.g. baby)","piggyback ride"]]},{"jlpt":[],"tags":[],"japanese":[{"word":"お負けに","reading":"おまけに"},{"word":"御負けに","reading":"おまけに"}],"senses":[["to make matters worse","besides","what's more","in addition","on top of that"]]},{"jlpt":["jlpt-n1"],"tags":[],"japanese":[{"word":"負債","reading":"ふさい"}],"senses":[["debt","liabilities"],["Liability (financial accounting)"]]},{"jlpt":["jlpt-n4"],"tags":["wanikani9"],"japanese":[{"word":"負ける","reading":"まける"},{"word":"敗ける","reading":"まける"},{"word":"敗北る","reading":"まける"}],"senses":[["to lose","to be defeated"],["to succumb","to give in","to surrender","to yield"],["to be inferior to"],["to break out in a rash due to (e.g. lacquer, shaving, etc.)"],["to reduce the price","to give a discount","to throw in (something extra) for free"]]},{"jlpt":["jlpt-n3"],"tags":[],"japanese":[{"word":"負け","reading":"まけ"}],"senses":[["defeat","loss","losing (a game)"],["failing to live up to (one's name, looks, etc.)"],["discount","loss (on a sale)"]]},{"jlpt":["jlpt-n2"],"tags":["wanikani9"],"japanese":[{"word":"勝負","reading":"しょうぶ"}],"senses":[["victory or defeat"],["match","contest","game","bout"],["Shoubu"]]},{"jlpt":["jlpt-n2","jlpt-n1"],"tags":[],"japanese":[{"word":"背負う","reading":"せおう"},{"word":"背負う","reading":"しょう"},{"word":"脊負う","reading":"せおう"},{"word":"脊負う","reading":"しょう"}],"senses":[["to carry on one's back"],["to be burdened with","to take responsibility for"],["to have (something) in the background","to be in front (of something)"],["to be conceited","to think highly of oneself"]]},{"jlpt":["jlpt-n1"],"tags":[],"japanese":[{"word":"負う","reading":"おう"}],"senses":[["to bear","to carry on one's back"],["to take responsibility for","to accept a duty"],["to receive (wound)","to incur (damage)","to be injured"],["to owe"]]},{"jlpt":["jlpt-n1"],"tags":[],"japanese":[{"word":"負傷","reading":"ふしょう"}],"senses":[["injury","wound"]]},{"jlpt":["jlpt-n1"],"tags":["wanikani24"],"japanese":[{"word":"負担","reading":"ふたん"}],"senses":[["burden","load","responsibility"],["bearing (a cost, responsibility, etc.)","shouldering"]]},{"jlpt":["jlpt-n1"],"tags":[],"japanese":[{"word":"負かす","reading":"まかす"}],"senses":[["to defeat"]]},{"jlpt":["jlpt-n1"],"tags":[],"japanese":[{"word":"お負け","reading":"おまけ"},{"word":"御負け","reading":"おまけ"}],"senses":[["freebie (e.g. with a purchase)","something additional","bonus","an extra"],["price reduction","discount"],["exaggeration"]]},{"jlpt":[],"tags":[],"japanese":[{"word":"負荷","reading":"ふか"}],"senses":[["burden","load (e.g. CPU time, electricity, etc.)"],["Load"]]},{"jlpt":[],"tags":[],"japanese":[{"word":"贔屓","reading":"ひいき"},{"word":"贔負","reading":"ひいき"}],"senses":[["favour","favor","patronage","favouritism","favoritism","partiality"],["favourite","favorite"],["patron","supporter","backer"],["Bixi (tortoise)"]]},{"jlpt":[],"tags":[],"japanese":[{"word":"顔負け","reading":"かおまけ"}],"senses":[["being put to shame","being outshone","being eclipsed","feeling embarrassed"]]},{"jlpt":[],"tags":[],"japanese":[{"word":"請け負う","reading":"うけおう"},{"word":"請負う","reading":"うけおう"}],"senses":[["to contract","to undertake"],["to take over","to take responsibility for"]]},{"jlpt":[],"tags":[],"japanese":[{"word":"抱負","reading":"ほうふ"}],"senses":[["aspiration","ambition","plan","hopes","wishes"]]},{"jlpt":[],"tags":[],"japanese":[{"word":"勝ち負け","reading":"かちまけ"}],"senses":[["victory or defeat","victory and defeat"]]},{"jlpt":[],"tags":[],"japanese":[{"word":"負","reading":"ふ"}],"senses":[["negative","minus"]]},{"jlpt":[],"tags":[],"japanese":[{"word":"自負","reading":"じふ"}],"senses":[["pride","self-confidence","thinking highly of oneself","being proud of one's abilities or achievements"]]},{"jlpt":[],"tags":[],"japanese":[{"word":"負んぶ","reading":"おんぶ"}],"senses":[["carrying on one's back (e.g. baby)","piggyback ride"]]},{"jlpt":[],"tags":[],"japanese":[{"word":"お負けに","reading":"おまけに"},{"word":"御負けに","reading":"おまけに"}],"senses":[["to make matters worse","besides","what's more","in addition","on top of that"]]},{"jlpt":[],"tags":[],"japanese":[{"word":"負い目","reading":"おいめ"},{"word":"負目","reading":"おいめ"}],"senses":[["(feeling of) indebtedness","feeling obliged"]]},{"jlpt":[],"tags":[],"japanese":[{"word":"請負","reading":"うけおい"},{"word":"請け負い","reading":"うけおい"}],"senses":[["contract (for work)","contracting","undertaking"]]},{"jlpt":[],"tags":[],"japanese":[{"word":"負け越し","reading":"まけこし"}],"senses":[["more losses than wins (sport)"]]},{"jlpt":[],"tags":[],"japanese":[{"word":"気負い","reading":"きおい"}],"senses":[["eagerness","enthusiasm","fervor","excitement","fighting spirit","fighting mood"]]}]}